{
	"global": {
		"settings": {
			"cecEvents": {
				"actions": [
					{
						"action": "Suspend",
						"event": "standby"
					},
					{
						"action": "Resume",
						"event": "set stream path"
					}
				],
				"enable": false
			},
			"effects": {
				"disable": [
					""
				],
				"paths": [
					"$ROOT/custom-effects"
				]
			},
			"flatbufServer": {
				"enable": true,
				"port": 19400,
				"timeout": 5
			},
			"forwarder": {
				"enable": false,
				"flatbuffer": [],
				"instance": 255,
				"instanceList": "NONE",
				"jsonapi": []
			},
			"framegrabber": {
				"available_devices": "X11",
				"cropBottom": 0,
				"cropLeft": 900,
				"cropRight": 1440,
				"cropTop": 0,
				"device": "x11",
				"device_inputs": "0",
				"enable": true,
				"fps": 25,
				"framerates": "25",
				"height": 1440,
				"input": 0,
				"pixelDecimation": 5,
				"resolutions": "0",
				"width": 4900
			},
			"general": {
				"configVersion": "2.1.2-beta.1",
				"name": "Ambilight",
				"showOptHelp": true,
				"watchedVersionBranch": "Stable"
			},
			"grabberAudio": {
				"audioEffect": "vuMeter",
				"device": "auto",
				"enable": false,
				"vuMeter": {
					"flip": "NO_CHANGE",
					"hotColor": [
						255,
						0,
						0
					],
					"multiplier": 1,
					"safeColor": [
						0,
						255,
						0
					],
					"safeValue": 45,
					"tolerance": 5,
					"warnColor": [
						255,
						255,
						0
					],
					"warnValue": 80
				}
			},
			"grabberV4L2": {
				"blueSignalThreshold": 0,
				"cropBottom": 0,
				"cropLeft": 0,
				"cropRight": 0,
				"cropTop": 0,
				"device": "none",
				"enable": false,
				"encoding": "NO_CHANGE",
				"flip": "NO_CHANGE",
				"fps": 15,
				"fpsSoftwareDecimation": 0,
				"greenSignalThreshold": 100,
				"hardware_brightness": 0,
				"hardware_contrast": 0,
				"hardware_hue": 0,
				"hardware_saturation": 0,
				"height": 0,
				"input": 0,
				"noSignalCounterThreshold": 200,
				"redSignalThreshold": 0,
				"sDHOffsetMax": 0.46,
				"sDHOffsetMin": 0.4,
				"sDVOffsetMax": 0.9,
				"sDVOffsetMin": 0.1,
				"signalDetection": false,
				"sizeDecimation": 8,
				"width": 0
			},
			"jsonServer": {
				"port": 19444
			},
			"logger": {
				"level": "warn"
			},
			"network": {
				"localApiAuth": false
			},
			"osEvents": {
				"lockEnable": true,
				"suspendEnable": true
			},
			"protoServer": {
				"enable": true,
				"port": 19445,
				"timeout": 5
			},
			"schedEvents": {
				"enable": false
			},
			"webConfig": {
				"crtPath": "",
				"document_root": "",
				"keyPassPhrase": "",
				"keyPath": "",
				"port": 8090,
				"sslPort": 8092
			}
		},
		"uuid": "cd01b6dc-ce97-5ecd-acab-9ea903d7087c"
	},
	"instanceIds": [
		0,
		1
	],
	"instances": [
		{
			"enabled": true,
			"id": 0,
			"name": "Ambilight - Monitor",
			"settings": {
				"backgroundEffect": {
					"color": [
						255,
						138,
						0
					],
					"effect": "Warm mood blobs",
					"enable": false,
					"type": "effect"
				},
				"blackborderdetector": {
					"blurRemoveCnt": 1,
					"borderFrameCnt": 50,
					"enable": true,
					"maxInconsistentCnt": 10,
					"mode": "default",
					"threshold": 5,
					"unknownFrameCnt": 600
				},
				"boblightServer": {
					"enable": false,
					"port": 19333,
					"priority": 128
				},
				"color": {
					"accuracyLevel": 4,
					"channelAdjustment": [
						{
							"backlightColored": false,
							"backlightThreshold": 5,
							"blue": [
								0,
								0,
								255
							],
							"brightness": 90,
							"brightnessCompensation": 90,
							"brightnessGain": 0.85,
							"cyan": [
								0,
								255,
								255
							],
							"gammaBlue": 1.9,
							"gammaGreen": 1.9,
							"gammaRed": 1.9,
							"green": [
								0,
								255,
								0
							],
							"id": "default",
							"leds": "*",
							"magenta": [
								255,
								0,
								255
							],
							"red": [
								255,
								0,
								0
							],
							"saturationGain": 1.3,
							"temperature": 6500,
							"white": [
								255,
								242,
								224
							],
							"yellow": [
								255,
								255,
								0
							]
						}
					],
					"imageToLedMappingType": "dominant_color_advanced",
					"reducedPixelSetFactorFactor": "0"
				},
				"device": {
					"autoStart": true,
					"colorOrder": "rgb",
					"enableAttempts": 6,
					"enableAttemptsInterval": 15,
					"hardwareLedCount": 113,
					"latchTime": 0,
					"output": "/dev/null",
					"printTimeStamp": false,
					"rewriteTime": 0,
					"type": "file"
				},
				"foregroundEffect": {
					"color": [
						0,
						0,
						255
					],
					"duration_ms": 3000,
					"effect": "Rainbow swirl fast",
					"enable": true,
					"type": "effect"
				},
				"instCapture": {
					"audioEnable": false,
					"audioGrabberDevice": "NONE",
					"audioPriority": 230,
					"systemEnable": true,
					"systemGrabberDevice": "NONE",
					"systemPriority": 250,
					"v4lEnable": false,
					"v4lGrabberDevice": "NONE",
					"v4lPriority": 240
				},
				"ledConfig": {
					"classic": {
						"bottom": 38,
						"edgegap": 0,
						"glength": 0,
						"gpos": 0,
						"hdepth": 8,
						"left": 20,
						"overlap": 0,
						"pblh": 0,
						"pblv": 100,
						"pbrh": 100,
						"pbrv": 100,
						"position": 55,
						"ptlh": 0,
						"ptlv": 0,
						"ptrh": 100,
						"ptrv": 0,
						"reverse": true,
						"right": 20,
						"top": 35,
						"vdepth": 6
					},
					"ledBlacklist": [],
					"matrix": {
						"cabling": "snake",
						"direction": "horizontal",
						"gapbottom": 0,
						"gapleft": 0,
						"gapright": 0,
						"gaptop": 0,
						"ledshoriz": 1,
						"ledsvert": 1,
						"start": "top-left"
					}
				},
				"leds": [
					{
						"hmax": 1,
						"hmin": 0.94,
						"vmax": 1,
						"vmin": 0.95
					},
					{
						"hmax": 1,
						"hmin": 0.94,
						"vmax": 0.95,
						"vmin": 0.9
					},
					{
						"hmax": 1,
						"hmin": 0.94,
						"vmax": 0.9,
						"vmin": 0.85
					},
					{
						"hmax": 1,
						"hmin": 0.94,
						"vmax": 0.85,
						"vmin": 0.8
					},
					{
						"hmax": 1,
						"hmin": 0.94,
						"vmax": 0.8,
						"vmin": 0.75
					},
					{
						"hmax": 1,
						"hmin": 0.94,
						"vmax": 0.75,
						"vmin": 0.7
					},
					{
						"hmax": 1,
						"hmin": 0.94,
						"vmax": 0.7,
						"vmin": 0.65
					},
					{
						"hmax": 1,
						"hmin": 0.94,
						"vmax": 0.65,
						"vmin": 0.6
					},
					{
						"hmax": 1,
						"hmin": 0.94,
						"vmax": 0.6,
						"vmin": 0.55
					},
					{
						"hmax": 1,
						"hmin": 0.94,
						"vmax": 0.55,
						"vmin": 0.5
					},
					{
						"hmax": 1,
						"hmin": 0.94,
						"vmax": 0.5,
						"vmin": 0.45
					},
					{
						"hmax": 1,
						"hmin": 0.94,
						"vmax": 0.45,
						"vmin": 0.4
					},
					{
						"hmax": 1,
						"hmin": 0.94,
						"vmax": 0.4,
						"vmin": 0.35
					},
					{
						"hmax": 1,
						"hmin": 0.94,
						"vmax": 0.35,
						"vmin": 0.3
					},
					{
						"hmax": 1,
						"hmin": 0.94,
						"vmax": 0.3,
						"vmin": 0.25
					},
					{
						"hmax": 1,
						"hmin": 0.94,
						"vmax": 0.25,
						"vmin": 0.2
					},
					{
						"hmax": 1,
						"hmin": 0.94,
						"vmax": 0.2,
						"vmin": 0.15
					},
					{
						"hmax": 1,
						"hmin": 0.94,
						"vmax": 0.15,
						"vmin": 0.1
					},
					{
						"hmax": 1,
						"hmin": 0.94,
						"vmax": 0.1,
						"vmin": 0.05
					},
					{
						"hmax": 1,
						"hmin": 0.94,
						"vmax": 0.05,
						"vmin": 0
					},
					{
						"hmax": 1,
						"hmin": 0.9714,
						"vmax": 0.08,
						"vmin": 0
					},
					{
						"hmax": 0.9714,
						"hmin": 0.9429,
						"vmax": 0.08,
						"vmin": 0
					},
					{
						"hmax": 0.9429,
						"hmin": 0.9143,
						"vmax": 0.08,
						"vmin": 0
					},
					{
						"hmax": 0.9143,
						"hmin": 0.8857,
						"vmax": 0.08,
						"vmin": 0
					},
					{
						"hmax": 0.8857,
						"hmin": 0.8571,
						"vmax": 0.08,
						"vmin": 0
					},
					{
						"hmax": 0.8571,
						"hmin": 0.8286,
						"vmax": 0.08,
						"vmin": 0
					},
					{
						"hmax": 0.8286,
						"hmin": 0.8,
						"vmax": 0.08,
						"vmin": 0
					},
					{
						"hmax": 0.8,
						"hmin": 0.7714,
						"vmax": 0.08,
						"vmin": 0
					},
					{
						"hmax": 0.7714,
						"hmin": 0.7429,
						"vmax": 0.08,
						"vmin": 0
					},
					{
						"hmax": 0.7429,
						"hmin": 0.7143,
						"vmax": 0.08,
						"vmin": 0
					},
					{
						"hmax": 0.7143,
						"hmin": 0.6857,
						"vmax": 0.08,
						"vmin": 0
					},
					{
						"hmax": 0.6857,
						"hmin": 0.6571,
						"vmax": 0.08,
						"vmin": 0
					},
					{
						"hmax": 0.6571,
						"hmin": 0.6286,
						"vmax": 0.08,
						"vmin": 0
					},
					{
						"hmax": 0.6286,
						"hmin": 0.6,
						"vmax": 0.08,
						"vmin": 0
					},
					{
						"hmax": 0.6,
						"hmin": 0.5714,
						"vmax": 0.08,
						"vmin": 0
					},
					{
						"hmax": 0.5714,
						"hmin": 0.5429,
						"vmax": 0.08,
						"vmin": 0
					},
					{
						"hmax": 0.5429,
						"hmin": 0.5143,
						"vmax": 0.08,
						"vmin": 0
					},
					{
						"hmax": 0.5143,
						"hmin": 0.4857,
						"vmax": 0.08,
						"vmin": 0
					},
					{
						"hmax": 0.4857,
						"hmin": 0.4571,
						"vmax": 0.08,
						"vmin": 0
					},
					{
						"hmax": 0.4571,
						"hmin": 0.4286,
						"vmax": 0.08,
						"vmin": 0
					},
					{
						"hmax": 0.4286,
						"hmin": 0.4,
						"vmax": 0.08,
						"vmin": 0
					},
					{
						"hmax": 0.4,
						"hmin": 0.3714,
						"vmax": 0.08,
						"vmin": 0
					},
					{
						"hmax": 0.3714,
						"hmin": 0.3429,
						"vmax": 0.08,
						"vmin": 0
					},
					{
						"hmax": 0.3429,
						"hmin": 0.3143,
						"vmax": 0.08,
						"vmin": 0
					},
					{
						"hmax": 0.3143,
						"hmin": 0.2857,
						"vmax": 0.08,
						"vmin": 0
					},
					{
						"hmax": 0.2857,
						"hmin": 0.2571,
						"vmax": 0.08,
						"vmin": 0
					},
					{
						"hmax": 0.2571,
						"hmin": 0.2286,
						"vmax": 0.08,
						"vmin": 0
					},
					{
						"hmax": 0.2286,
						"hmin": 0.2,
						"vmax": 0.08,
						"vmin": 0
					},
					{
						"hmax": 0.2,
						"hmin": 0.1714,
						"vmax": 0.08,
						"vmin": 0
					},
					{
						"hmax": 0.1714,
						"hmin": 0.1429,
						"vmax": 0.08,
						"vmin": 0
					},
					{
						"hmax": 0.1429,
						"hmin": 0.1143,
						"vmax": 0.08,
						"vmin": 0
					},
					{
						"hmax": 0.1143,
						"hmin": 0.0857,
						"vmax": 0.08,
						"vmin": 0
					},
					{
						"hmax": 0.0857,
						"hmin": 0.0571,
						"vmax": 0.08,
						"vmin": 0
					},
					{
						"hmax": 0.0571,
						"hmin": 0.0286,
						"vmax": 0.08,
						"vmin": 0
					},
					{
						"hmax": 0.0286,
						"hmin": 0,
						"vmax": 0.08,
						"vmin": 0
					},
					{
						"hmax": 0.06,
						"hmin": 0,
						"vmax": 0.05,
						"vmin": 0
					},
					{
						"hmax": 0.06,
						"hmin": 0,
						"vmax": 0.1,
						"vmin": 0.05
					},
					{
						"hmax": 0.06,
						"hmin": 0,
						"vmax": 0.15,
						"vmin": 0.1
					},
					{
						"hmax": 0.06,
						"hmin": 0,
						"vmax": 0.2,
						"vmin": 0.15
					},
					{
						"hmax": 0.06,
						"hmin": 0,
						"vmax": 0.25,
						"vmin": 0.2
					},
					{
						"hmax": 0.06,
						"hmin": 0,
						"vmax": 0.3,
						"vmin": 0.25
					},
					{
						"hmax": 0.06,
						"hmin": 0,
						"vmax": 0.35,
						"vmin": 0.3
					},
					{
						"hmax": 0.06,
						"hmin": 0,
						"vmax": 0.4,
						"vmin": 0.35
					},
					{
						"hmax": 0.06,
						"hmin": 0,
						"vmax": 0.45,
						"vmin": 0.4
					},
					{
						"hmax": 0.06,
						"hmin": 0,
						"vmax": 0.5,
						"vmin": 0.45
					},
					{
						"hmax": 0.06,
						"hmin": 0,
						"vmax": 0.55,
						"vmin": 0.5
					},
					{
						"hmax": 0.06,
						"hmin": 0,
						"vmax": 0.6,
						"vmin": 0.55
					},
					{
						"hmax": 0.06,
						"hmin": 0,
						"vmax": 0.65,
						"vmin": 0.6
					},
					{
						"hmax": 0.06,
						"hmin": 0,
						"vmax": 0.7,
						"vmin": 0.65
					},
					{
						"hmax": 0.06,
						"hmin": 0,
						"vmax": 0.75,
						"vmin": 0.7
					},
					{
						"hmax": 0.06,
						"hmin": 0,
						"vmax": 0.8,
						"vmin": 0.75
					},
					{
						"hmax": 0.06,
						"hmin": 0,
						"vmax": 0.85,
						"vmin": 0.8
					},
					{
						"hmax": 0.06,
						"hmin": 0,
						"vmax": 0.9,
						"vmin": 0.85
					},
					{
						"hmax": 0.06,
						"hmin": 0,
						"vmax": 0.95,
						"vmin": 0.9
					},
					{
						"hmax": 0.06,
						"hmin": 0,
						"vmax": 1,
						"vmin": 0.95
					},
					{
						"hmax": 0.0263,
						"hmin": 0,
						"vmax": 1,
						"vmin": 0.92
					},
					{
						"hmax": 0.0526,
						"hmin": 0.0263,
						"vmax": 1,
						"vmin": 0.92
					},
					{
						"hmax": 0.0789,
						"hmin": 0.0526,
						"vmax": 1,
						"vmin": 0.92
					},
					{
						"hmax": 0.1053,
						"hmin": 0.0789,
						"vmax": 1,
						"vmin": 0.92
					},
					{
						"hmax": 0.1316,
						"hmin": 0.1053,
						"vmax": 1,
						"vmin": 0.92
					},
					{
						"hmax": 0.1579,
						"hmin": 0.1316,
						"vmax": 1,
						"vmin": 0.92
					},
					{
						"hmax": 0.1842,
						"hmin": 0.1579,
						"vmax": 1,
						"vmin": 0.92
					},
					{
						"hmax": 0.2105,
						"hmin": 0.1842,
						"vmax": 1,
						"vmin": 0.92
					},
					{
						"hmax": 0.2368,
						"hmin": 0.2105,
						"vmax": 1,
						"vmin": 0.92
					},
					{
						"hmax": 0.2632,
						"hmin": 0.2368,
						"vmax": 1,
						"vmin": 0.92
					},
					{
						"hmax": 0.2895,
						"hmin": 0.2632,
						"vmax": 1,
						"vmin": 0.92
					},
					{
						"hmax": 0.3158,
						"hmin": 0.2895,
						"vmax": 1,
						"vmin": 0.92
					},
					{
						"hmax": 0.3421,
						"hmin": 0.3158,
						"vmax": 1,
						"vmin": 0.92
					},
					{
						"hmax": 0.3684,
						"hmin": 0.3421,
						"vmax": 1,
						"vmin": 0.92
					},
					{
						"hmax": 0.3947,
						"hmin": 0.3684,
						"vmax": 1,
						"vmin": 0.92
					},
					{
						"hmax": 0.4211,
						"hmin": 0.3947,
						"vmax": 1,
						"vmin": 0.92
					},
					{
						"hmax": 0.4474,
						"hmin": 0.4211,
						"vmax": 1,
						"vmin": 0.92
					},
					{
						"hmax": 0.4737,
						"hmin": 0.4474,
						"vmax": 1,
						"vmin": 0.92
					},
					{
						"hmax": 0.5,
						"hmin": 0.4737,
						"vmax": 1,
						"vmin": 0.92
					},
					{
						"hmax": 0.5263,
						"hmin": 0.5,
						"vmax": 1,
						"vmin": 0.92
					},
					{
						"hmax": 0.5526,
						"hmin": 0.5263,
						"vmax": 1,
						"vmin": 0.92
					},
					{
						"hmax": 0.5789,
						"hmin": 0.5526,
						"vmax": 1,
						"vmin": 0.92
					},
					{
						"hmax": 0.6053,
						"hmin": 0.5789,
						"vmax": 1,
						"vmin": 0.92
					},
					{
						"hmax": 0.6316,
						"hmin": 0.6053,
						"vmax": 1,
						"vmin": 0.92
					},
					{
						"hmax": 0.6579,
						"hmin": 0.6316,
						"vmax": 1,
						"vmin": 0.92
					},
					{
						"hmax": 0.6842,
						"hmin": 0.6579,
						"vmax": 1,
						"vmin": 0.92
					},
					{
						"hmax": 0.7105,
						"hmin": 0.6842,
						"vmax": 1,
						"vmin": 0.92
					},
					{
						"hmax": 0.7368,
						"hmin": 0.7105,
						"vmax": 1,
						"vmin": 0.92
					},
					{
						"hmax": 0.7632,
						"hmin": 0.7368,
						"vmax": 1,
						"vmin": 0.92
					},
					{
						"hmax": 0.7895,
						"hmin": 0.7632,
						"vmax": 1,
						"vmin": 0.92
					},
					{
						"hmax": 0.8158,
						"hmin": 0.7895,
						"vmax": 1,
						"vmin": 0.92
					},
					{
						"hmax": 0.8421,
						"hmin": 0.8158,
						"vmax": 1,
						"vmin": 0.92
					},
					{
						"hmax": 0.8684,
						"hmin": 0.8421,
						"vmax": 1,
						"vmin": 0.92
					},
					{
						"hmax": 0.8947,
						"hmin": 0.8684,
						"vmax": 1,
						"vmin": 0.92
					},
					{
						"hmax": 0.9211,
						"hmin": 0.8947,
						"vmax": 1,
						"vmin": 0.92
					},
					{
						"hmax": 0.9474,
						"hmin": 0.9211,
						"vmax": 1,
						"vmin": 0.92
					},
					{
						"hmax": 0.9737,
						"hmin": 0.9474,
						"vmax": 1,
						"vmin": 0.92
					},
					{
						"hmax": 1,
						"hmin": 0.9737,
						"vmax": 1,
						"vmin": 0.92
					}
				],
				"smoothing": {
					"decay": 1,
					"dithering": false,
					"enable": true,
					"interpolationRate": 1,
					"time_ms": 1000,
					"type": "decay",
					"updateDelay": 0,
					"updateFrequency": 30
				}
			}
		},
		{
			"enabled": true,
			"id": 1,
			"name": "Ambilight - Escritorio",
			"settings": {
				"backgroundEffect": {
					"color": [
						255,
						138,
						0
					],
					"effect": "Warm mood blobs",
					"enable": false,
					"type": "effect"
				},
				"blackborderdetector": {
					"blurRemoveCnt": 1,
					"borderFrameCnt": 50,
					"enable": true,
					"maxInconsistentCnt": 10,
					"mode": "default",
					"threshold": 5,
					"unknownFrameCnt": 600
				},
				"boblightServer": {
					"enable": false,
					"port": 19333,
					"priority": 128
				},
				"color": {
					"accuracyLevel": 4,
					"channelAdjustment": [
						{
							"backlightColored": false,
							"backlightThreshold": 3,
							"blue": [
								0,
								0,
								255
							],
							"brightness": 100,
							"brightnessCompensation": 100,
							"brightnessGain": 0.8,
							"cyan": [
								0,
								255,
								255
							],
							"gammaBlue": 1.8,
							"gammaGreen": 1.8,
							"gammaRed": 1.8,
							"green": [
								0,
								255,
								0
							],
							"id": "default",
							"leds": "*",
							"magenta": [
								255,
								0,
								255
							],
							"red": [
								255,
								0,
								0
							],
							"saturationGain": 1.5,
							"temperature": 6600,
							"white": [
								255,
								242,
								224
							],
							"yellow": [
								255,
								255,
								0
							]
						}
					],
					"imageToLedMappingType": "dominant_color_advanced",
					"reducedPixelSetFactorFactor": "0"
				},
				"device": {
					"autoStart": true,
					"colorOrder": "rgb",
					"enableAttempts": 6,
					"enableAttemptsInterval": 15,
					"hardwareLedCount": 120,
					"latchTime": 0,
					"output": "/dev/null",
					"printTimeStamp": false,
					"rewriteTime": 0,
					"type": "file"
				},
				"foregroundEffect": {
					"color": [
						0,
						0,
						255
					],
					"duration_ms": 3000,
					"effect": "Rainbow swirl fast",
					"enable": true,
					"type": "effect"
				},
				"instCapture": {
					"audioEnable": false,
					"audioGrabberDevice": "NONE",
					"audioPriority": 230,
					"systemEnable": true,
					"systemGrabberDevice": "NONE",
					"systemPriority": 250,
					"v4lEnable": false,
					"v4lGrabberDevice": "NONE",
					"v4lPriority": 240
				},
				"ledConfig": {
					"classic": {
						"bottom": 0,
						"edgegap": 0,
						"glength": 0,
						"gpos": 0,
						"hdepth": 8,
						"left": 0,
						"overlap": 0,
						"pblh": 0,
						"pblv": 100,
						"pbrh": 100,
						"pbrv": 100,
						"position": 0,
						"ptlh": 0,
						"ptlv": 0,
						"ptrh": 100,
						"ptrv": 0,
						"reverse": false,
						"right": 0,
						"top": 1,
						"vdepth": 5
					},
					"ledBlacklist": [],
					"matrix": {
						"cabling": "snake",
						"direction": "horizontal",
						"gapbottom": 0,
						"gapleft": 0,
						"gapright": 0,
						"gaptop": 90,
						"ledshoriz": 120,
						"ledsvert": 1,
						"start": "bottom-right"
					}
				},
				"leds": [
					{
						"hmax": 1,
						"hmin": 0.9917,
						"vmax": 1,
						"vmin": 0.9
					},
					{
						"hmax": 0.9917,
						"hmin": 0.9833,
						"vmax": 1,
						"vmin": 0.9
					},
					{
						"hmax": 0.9833,
						"hmin": 0.975,
						"vmax": 1,
						"vmin": 0.9
					},
					{
						"hmax": 0.975,
						"hmin": 0.9667,
						"vmax": 1,
						"vmin": 0.9
					},
					{
						"hmax": 0.9667,
						"hmin": 0.9583,
						"vmax": 1,
						"vmin": 0.9
					},
					{
						"hmax": 0.9583,
						"hmin": 0.95,
						"vmax": 1,
						"vmin": 0.9
					},
					{
						"hmax": 0.95,
						"hmin": 0.9417,
						"vmax": 1,
						"vmin": 0.9
					},
					{
						"hmax": 0.9417,
						"hmin": 0.9333,
						"vmax": 1,
						"vmin": 0.9
					},
					{
						"hmax": 0.9333,
						"hmin": 0.925,
						"vmax": 1,
						"vmin": 0.9
					},
					{
						"hmax": 0.925,
						"hmin": 0.9167,
						"vmax": 1,
						"vmin": 0.9
					},
					{
						"hmax": 0.9167,
						"hmin": 0.9083,
						"vmax": 1,
						"vmin": 0.9
					},
					{
						"hmax": 0.9083,
						"hmin": 0.9,
						"vmax": 1,
						"vmin": 0.9
					},
					{
						"hmax": 0.9,
						"hmin": 0.8917,
						"vmax": 1,
						"vmin": 0.9
					},
					{
						"hmax": 0.8917,
						"hmin": 0.8833,
						"vmax": 1,
						"vmin": 0.9
					},
					{
						"hmax": 0.8833,
						"hmin": 0.875,
						"vmax": 1,
						"vmin": 0.9
					},
					{
						"hmax": 0.875,
						"hmin": 0.8667,
						"vmax": 1,
						"vmin": 0.9
					},
					{
						"hmax": 0.8667,
						"hmin": 0.8583,
						"vmax": 1,
						"vmin": 0.9
					},
					{
						"hmax": 0.8583,
						"hmin": 0.85,
						"vmax": 1,
						"vmin": 0.9
					},
					{
						"hmax": 0.85,
						"hmin": 0.8417,
						"vmax": 1,
						"vmin": 0.9
					},
					{
						"hmax": 0.8417,
						"hmin": 0.8333,
						"vmax": 1,
						"vmin": 0.9
					},
					{
						"hmax": 0.8333,
						"hmin": 0.825,
						"vmax": 1,
						"vmin": 0.9
					},
					{
						"hmax": 0.825,
						"hmin": 0.8167,
						"vmax": 1,
						"vmin": 0.9
					},
					{
						"hmax": 0.8167,
						"hmin": 0.8083,
						"vmax": 1,
						"vmin": 0.9
					},
					{
						"hmax": 0.8083,
						"hmin": 0.8,
						"vmax": 1,
						"vmin": 0.9
					},
					{
						"hmax": 0.8,
						"hmin": 0.7917,
						"vmax": 1,
						"vmin": 0.9
					},
					{
						"hmax": 0.7917,
						"hmin": 0.7833,
						"vmax": 1,
						"vmin": 0.9
					},
					{
						"hmax": 0.7833,
						"hmin": 0.775,
						"vmax": 1,
						"vmin": 0.9
					},
					{
						"hmax": 0.775,
						"hmin": 0.7667,
						"vmax": 1,
						"vmin": 0.9
					},
					{
						"hmax": 0.7667,
						"hmin": 0.7583,
						"vmax": 1,
						"vmin": 0.9
					},
					{
						"hmax": 0.7583,
						"hmin": 0.75,
						"vmax": 1,
						"vmin": 0.9
					},
					{
						"hmax": 0.75,
						"hmin": 0.7417,
						"vmax": 1,
						"vmin": 0.9
					},
					{
						"hmax": 0.7417,
						"hmin": 0.7333,
						"vmax": 1,
						"vmin": 0.9
					},
					{
						"hmax": 0.7333,
						"hmin": 0.725,
						"vmax": 1,
						"vmin": 0.9
					},
					{
						"hmax": 0.725,
						"hmin": 0.7167,
						"vmax": 1,
						"vmin": 0.9
					},
					{
						"hmax": 0.7167,
						"hmin": 0.7083,
						"vmax": 1,
						"vmin": 0.9
					},
					{
						"hmax": 0.7083,
						"hmin": 0.7,
						"vmax": 1,
						"vmin": 0.9
					},
					{
						"hmax": 0.7,
						"hmin": 0.6917,
						"vmax": 1,
						"vmin": 0.9
					},
					{
						"hmax": 0.6917,
						"hmin": 0.6833,
						"vmax": 1,
						"vmin": 0.9
					},
					{
						"hmax": 0.6833,
						"hmin": 0.675,
						"vmax": 1,
						"vmin": 0.9
					},
					{
						"hmax": 0.675,
						"hmin": 0.6667,
						"vmax": 1,
						"vmin": 0.9
					},
					{
						"hmax": 0.6667,
						"hmin": 0.6583,
						"vmax": 1,
						"vmin": 0.9
					},
					{
						"hmax": 0.6583,
						"hmin": 0.65,
						"vmax": 1,
						"vmin": 0.9
					},
					{
						"hmax": 0.65,
						"hmin": 0.6417,
						"vmax": 1,
						"vmin": 0.9
					},
					{
						"hmax": 0.6417,
						"hmin": 0.6333,
						"vmax": 1,
						"vmin": 0.9
					},
					{
						"hmax": 0.6333,
						"hmin": 0.625,
						"vmax": 1,
						"vmin": 0.9
					},
					{
						"hmax": 0.625,
						"hmin": 0.6167,
						"vmax": 1,
						"vmin": 0.9
					},
					{
						"hmax": 0.6167,
						"hmin": 0.6083,
						"vmax": 1,
						"vmin": 0.9
					},
					{
						"hmax": 0.6083,
						"hmin": 0.6,
						"vmax": 1,
						"vmin": 0.9
					},
					{
						"hmax": 0.6,
						"hmin": 0.5917,
						"vmax": 1,
						"vmin": 0.9
					},
					{
						"hmax": 0.5917,
						"hmin": 0.5833,
						"vmax": 1,
						"vmin": 0.9
					},
					{
						"hmax": 0.5833,
						"hmin": 0.575,
						"vmax": 1,
						"vmin": 0.9
					},
					{
						"hmax": 0.575,
						"hmin": 0.5667,
						"vmax": 1,
						"vmin": 0.9
					},
					{
						"hmax": 0.5667,
						"hmin": 0.5583,
						"vmax": 1,
						"vmin": 0.9
					},
					{
						"hmax": 0.5583,
						"hmin": 0.55,
						"vmax": 1,
						"vmin": 0.9
					},
					{
						"hmax": 0.55,
						"hmin": 0.5417,
						"vmax": 1,
						"vmin": 0.9
					},
					{
						"hmax": 0.5417,
						"hmin": 0.5333,
						"vmax": 1,
						"vmin": 0.9
					},
					{
						"hmax": 0.5333,
						"hmin": 0.525,
						"vmax": 1,
						"vmin": 0.9
					},
					{
						"hmax": 0.525,
						"hmin": 0.5167,
						"vmax": 1,
						"vmin": 0.9
					},
					{
						"hmax": 0.5167,
						"hmin": 0.5083,
						"vmax": 1,
						"vmin": 0.9
					},
					{
						"hmax": 0.5083,
						"hmin": 0.5,
						"vmax": 1,
						"vmin": 0.9
					},
					{
						"hmax": 0.5,
						"hmin": 0.4917,
						"vmax": 1,
						"vmin": 0.9
					},
					{
						"hmax": 0.4917,
						"hmin": 0.4833,
						"vmax": 1,
						"vmin": 0.9
					},
					{
						"hmax": 0.4833,
						"hmin": 0.475,
						"vmax": 1,
						"vmin": 0.9
					},
					{
						"hmax": 0.475,
						"hmin": 0.4667,
						"vmax": 1,
						"vmin": 0.9
					},
					{
						"hmax": 0.4667,
						"hmin": 0.4583,
						"vmax": 1,
						"vmin": 0.9
					},
					{
						"hmax": 0.4583,
						"hmin": 0.45,
						"vmax": 1,
						"vmin": 0.9
					},
					{
						"hmax": 0.45,
						"hmin": 0.4417,
						"vmax": 1,
						"vmin": 0.9
					},
					{
						"hmax": 0.4417,
						"hmin": 0.4333,
						"vmax": 1,
						"vmin": 0.9
					},
					{
						"hmax": 0.4333,
						"hmin": 0.425,
						"vmax": 1,
						"vmin": 0.9
					},
					{
						"hmax": 0.425,
						"hmin": 0.4167,
						"vmax": 1,
						"vmin": 0.9
					},
					{
						"hmax": 0.4167,
						"hmin": 0.4083,
						"vmax": 1,
						"vmin": 0.9
					},
					{
						"hmax": 0.4083,
						"hmin": 0.4,
						"vmax": 1,
						"vmin": 0.9
					},
					{
						"hmax": 0.4,
						"hmin": 0.3917,
						"vmax": 1,
						"vmin": 0.9
					},
					{
						"hmax": 0.3917,
						"hmin": 0.3833,
						"vmax": 1,
						"vmin": 0.9
					},
					{
						"hmax": 0.3833,
						"hmin": 0.375,
						"vmax": 1,
						"vmin": 0.9
					},
					{
						"hmax": 0.375,
						"hmin": 0.3667,
						"vmax": 1,
						"vmin": 0.9
					},
					{
						"hmax": 0.3667,
						"hmin": 0.3583,
						"vmax": 1,
						"vmin": 0.9
					},
					{
						"hmax": 0.3583,
						"hmin": 0.35,
						"vmax": 1,
						"vmin": 0.9
					},
					{
						"hmax": 0.35,
						"hmin": 0.3417,
						"vmax": 1,
						"vmin": 0.9
					},
					{
						"hmax": 0.3417,
						"hmin": 0.3333,
						"vmax": 1,
						"vmin": 0.9
					},
					{
						"hmax": 0.3333,
						"hmin": 0.325,
						"vmax": 1,
						"vmin": 0.9
					},
					{
						"hmax": 0.325,
						"hmin": 0.3167,
						"vmax": 1,
						"vmin": 0.9
					},
					{
						"hmax": 0.3167,
						"hmin": 0.3083,
						"vmax": 1,
						"vmin": 0.9
					},
					{
						"hmax": 0.3083,
						"hmin": 0.3,
						"vmax": 1,
						"vmin": 0.9
					},
					{
						"hmax": 0.3,
						"hmin": 0.2917,
						"vmax": 1,
						"vmin": 0.9
					},
					{
						"hmax": 0.2917,
						"hmin": 0.2833,
						"vmax": 1,
						"vmin": 0.9
					},
					{
						"hmax": 0.2833,
						"hmin": 0.275,
						"vmax": 1,
						"vmin": 0.9
					},
					{
						"hmax": 0.275,
						"hmin": 0.2667,
						"vmax": 1,
						"vmin": 0.9
					},
					{
						"hmax": 0.2667,
						"hmin": 0.2583,
						"vmax": 1,
						"vmin": 0.9
					},
					{
						"hmax": 0.2583,
						"hmin": 0.25,
						"vmax": 1,
						"vmin": 0.9
					},
					{
						"hmax": 0.25,
						"hmin": 0.2417,
						"vmax": 1,
						"vmin": 0.9
					},
					{
						"hmax": 0.2417,
						"hmin": 0.2333,
						"vmax": 1,
						"vmin": 0.9
					},
					{
						"hmax": 0.2333,
						"hmin": 0.225,
						"vmax": 1,
						"vmin": 0.9
					},
					{
						"hmax": 0.225,
						"hmin": 0.2167,
						"vmax": 1,
						"vmin": 0.9
					},
					{
						"hmax": 0.2167,
						"hmin": 0.2083,
						"vmax": 1,
						"vmin": 0.9
					},
					{
						"hmax": 0.2083,
						"hmin": 0.2,
						"vmax": 1,
						"vmin": 0.9
					},
					{
						"hmax": 0.2,
						"hmin": 0.1917,
						"vmax": 1,
						"vmin": 0.9
					},
					{
						"hmax": 0.1917,
						"hmin": 0.1833,
						"vmax": 1,
						"vmin": 0.9
					},
					{
						"hmax": 0.1833,
						"hmin": 0.175,
						"vmax": 1,
						"vmin": 0.9
					},
					{
						"hmax": 0.175,
						"hmin": 0.1667,
						"vmax": 1,
						"vmin": 0.9
					},
					{
						"hmax": 0.1667,
						"hmin": 0.1583,
						"vmax": 1,
						"vmin": 0.9
					},
					{
						"hmax": 0.1583,
						"hmin": 0.15,
						"vmax": 1,
						"vmin": 0.9
					},
					{
						"hmax": 0.15,
						"hmin": 0.1417,
						"vmax": 1,
						"vmin": 0.9
					},
					{
						"hmax": 0.1417,
						"hmin": 0.1333,
						"vmax": 1,
						"vmin": 0.9
					},
					{
						"hmax": 0.1333,
						"hmin": 0.125,
						"vmax": 1,
						"vmin": 0.9
					},
					{
						"hmax": 0.125,
						"hmin": 0.1167,
						"vmax": 1,
						"vmin": 0.9
					},
					{
						"hmax": 0.1167,
						"hmin": 0.1083,
						"vmax": 1,
						"vmin": 0.9
					},
					{
						"hmax": 0.1083,
						"hmin": 0.1,
						"vmax": 1,
						"vmin": 0.9
					},
					{
						"hmax": 0.1,
						"hmin": 0.0917,
						"vmax": 1,
						"vmin": 0.9
					},
					{
						"hmax": 0.0917,
						"hmin": 0.0833,
						"vmax": 1,
						"vmin": 0.9
					},
					{
						"hmax": 0.0833,
						"hmin": 0.075,
						"vmax": 1,
						"vmin": 0.9
					},
					{
						"hmax": 0.075,
						"hmin": 0.0667,
						"vmax": 1,
						"vmin": 0.9
					},
					{
						"hmax": 0.0667,
						"hmin": 0.0583,
						"vmax": 1,
						"vmin": 0.9
					},
					{
						"hmax": 0.0583,
						"hmin": 0.05,
						"vmax": 1,
						"vmin": 0.9
					},
					{
						"hmax": 0.05,
						"hmin": 0.0417,
						"vmax": 1,
						"vmin": 0.9
					},
					{
						"hmax": 0.0417,
						"hmin": 0.0333,
						"vmax": 1,
						"vmin": 0.9
					},
					{
						"hmax": 0.0333,
						"hmin": 0.025,
						"vmax": 1,
						"vmin": 0.9
					},
					{
						"hmax": 0.025,
						"hmin": 0.0167,
						"vmax": 1,
						"vmin": 0.9
					},
					{
						"hmax": 0.0167,
						"hmin": 0.0083,
						"vmax": 1,
						"vmin": 0.9
					},
					{
						"hmax": 0.0083,
						"hmin": 0,
						"vmax": 1,
						"vmin": 0.9
					}
				],
				"smoothing": {
					"decay": 1,
					"dithering": false,
					"enable": true,
					"interpolationRate": 25,
					"time_ms": 150,
					"type": "linear",
					"updateDelay": 0,
					"updateFrequency": 25
				}
			}
		}
	]
}